{
  "version": "3.3.10",
  "flags": {},
  "shapes": [
    {
      "label": "waybill",
      "score": 0.9744877815246582,
      "points": [
        [
          1128.0,
          1122.0
        ],
        [
          1096.0314960629921,
          1099.0551181102362
        ],
        [
          612.0,
          1561.0
        ],
        [
          589.5584415584416,
          1585.064935064935
        ],
        [
          588.2597402597403,
          1605.1948051948052
        ],
        [
          981.1168831168832,
          1962.3376623376623
        ],
        [
          1116.0,
          1823.0
        ],
        [
          1283.064935064935,
          1647.4025974025974
        ],
        [
          1473.0,
          1440.0
        ],
        [
          1313.5844155844154,
          1285.7142857142858
        ],
        [
          1259.038961038961,
          1242.2077922077922
        ]
      ],
      "group_id": null,
      "description": null,
      "difficult": false,
      "shape_type": "polygon",
      "flags": {},
      "attributes": {},
      "kie_linking": []
    }
  ],
  "imagePath": "..\\bvn\\images\\train\\005-0-2.jpg",
  "imageData": null,
  "imageHeight": 4080,
  "imageWidth": 2296
}